charmcraftcache/__init__.py
charmcraftcache/_main.py
charmcraftcache/_platforms.py
charmcraftcache-0.8.0.dist-info/METADATA
charmcraftcache-0.8.0.dist-info/WHEEL
charmcraftcache-0.8.0.dist-info/entry_points.txt
charmcraftcache-0.8.0.dist-info/licenses/LICENSE
charmcraftcache-0.8.0.dist-info/RECORD
