Metadata-Version: 2.4
Name: charmcraftcache
Version: 0.8.0
Summary: Fast first-time builds for charmcraft
License-File: LICENSE
Author: Carl Csaposs
Author-email: carl.csaposs@canonical.com
Requires-Python: >=3.10
Classifier: Programming Language :: Python :: 3
Classifier: Programming Language :: Python :: 3.10
Classifier: Programming Language :: Python :: 3.11
Classifier: Programming Language :: Python :: 3.12
Classifier: Programming Language :: Python :: 3.13
Classifier: Programming Language :: Python :: 3.14
Requires-Dist: packaging (>=24.2)
Requires-Dist: pyyaml (>=6.0.2)
Requires-Dist: requests (>=2.32.3)
Requires-Dist: typer (>=0.15.1)
Project-URL: Repository, https://github.com/canonical/charmcraftcache
